src/__init__.py
src/Core/BitboardUtility.py
src/Core/Board.py
src/Core/GameState.py
src/Core/Move.py
src/Core/MoveGeneration.py
src/Core/Perft.py
src/Core/Piece.py
src/Core/PieceList.py
src/Core/PrecomputedAttacks.py
src/Core/__init__.py
bit_chess_python-0.1.1.dist-info/METADATA
bit_chess_python-0.1.1.dist-info/WHEEL
bit_chess_python-0.1.1.dist-info/top_level.txt
bit_chess_python-0.1.1.dist-info/RECORD
