Metadata-Version: 2.1
Name: bit-chess-python
Version: 0.1.1
Summary: Bitboard Chess implementation written entirely in Python
Author: Andrew Yin
Author-email: andrewyingo@gmail.com
Classifier: Programming Language :: Python :: 3
Classifier: License :: OSI Approved :: MIT License
Classifier: Operating System :: OS Independent
Requires-Python: >=3.9
